typing_master_terminal-1.0.3.dist-info/licenses/LICENSE
typing_test/__init__.py
typing_test/main.py
typing_test/words.py
typing_master_terminal-1.0.3.dist-info/METADATA
typing_master_terminal-1.0.3.dist-info/WHEEL
typing_master_terminal-1.0.3.dist-info/entry_points.txt
typing_master_terminal-1.0.3.dist-info/top_level.txt
typing_master_terminal-1.0.3.dist-info/RECORD
